{
    "url": "http:\/\/m.dbacks.mlb.com\/news\/article\/40993036\/giants-coach-tim-flannery-to-hold-benefit-shows-for-bryan-stow\/",
    "title": "Giants coach Flannery to hold benefit shows for Stow",
    "subtitle": "",
    "body": "SAN FRANCISCO -- Giants third-base coach Tim Flannery, who doubles as an accomplished musician, will continue his efforts to help Bryan Stow by performing in three upcoming northern California concerts to benefit the seriously injured man.  The benefits are slated for Thursday, Jan. 24, at Redwood City's Fox Theatre (www.foxrwc.com); Saturday, Jan. 26 at Napa's Uptown Theatre (www.uptowntheatrenapa.com), and Sunday, Jan. 27 at Santa Cruz's Kuumbwa Jazz (www.kuumbwajazz.org). Flannery also will take the stage on Friday, Jan. 25 at Mill Valley's Sweetwater Music Hall (www.sweetwatermusichall.com). Chris Haft is a reporter for MLB.com. This story was not subject to the approval of Major League Baseball or its clubs.",
    "author": "Chris Haft"
}
